pommes_craft/__init__.py
pommes_craft/components/__init__.py
pommes_craft/components/area.py
pommes_craft/components/carbon.py
pommes_craft/components/combined_technology.py
pommes_craft/components/conversion_technology.py
pommes_craft/components/demand.py
pommes_craft/components/economic_hypothesis.py
pommes_craft/components/flexibility.py
pommes_craft/components/link.py
pommes_craft/components/load_shedding.py
pommes_craft/components/net_import.py
pommes_craft/components/spillage.py
pommes_craft/components/storage_technology.py
pommes_craft/components/time_step_manager.py
pommes_craft/components/transport_technology.py
pommes_craft/components/turpe.py
pommes_craft/core/__init__.py
pommes_craft/core/component.py
pommes_craft/core/model.py
pommes_craft/core/model_context.py
pommes_craft/data/examples/test_case/test.py
pommes_craft/data/examples/test_case/pre_process/pre_process.py
pommes_craft/data/examples/test_case/pre_process/revert_pre_process.py
pommes_craft/helpers/__init__.py
pommes_craft/helpers/hydro_inflow.py
pommes_craft/tests/__init__.py
pommes_craft/tests/conftest.py
pommes_craft/tests/components/__init__.py
pommes_craft/tests/components/test_area.py
pommes_craft/tests/components/test_conversion_technology.py
pommes_craft/tests/components/test_link.py
pommes_craft/tests/components/test_storage_technology.py
pommes_craft/tests/components/test_time_step_manager.py
pommes_craft/tests/core/__init__.py
pommes_craft/tests/core/test_component.py
pommes_craft/tests/core/test_energy_model.py
pommes_craft/tests/core/test_model.py
pommes_craft/tests/systems/__init__.py
pommes_craft/tests/systems/test_flexible_demand.py
pommes_craft/tests/systems/test_load_shedding.py
pommes_craft/tests/systems/test_multi_resource_system.py
pommes_craft/tests/systems/test_one_area_combined_tech.py
pommes_craft/tests/systems/test_one_area_conversion_tech.py
pommes_craft/tests/systems/test_one_area_storage.py
pommes_craft/tests/systems/test_two_areas_with_link.py
pommes_craft-0.3.0.dist-info/licenses/LICENCE.md
pommes_craft-0.3.0.dist-info/METADATA
pommes_craft-0.3.0.dist-info/WHEEL
pommes_craft-0.3.0.dist-info/top_level.txt
pommes_craft-0.3.0.dist-info/RECORD
