Metadata-Version: 2.4
Name: pommes_craft
Version: 0.3.0
Summary: High-level interface to the POMMES energy system modeling tool
Author-email: Yassine Abdelouadoud <yassine.abdelouadoud@minesparis.psl.eu>
Requires-Python: >=3.10
License-File: LICENCE.md
Requires-Dist: polars>=0.18.0
Requires-Dist: pyyaml>=6.0
Requires-Dist: matplotlib>=3.5.0
Requires-Dist: numpy>=1.20.0
Requires-Dist: pyarrow
Requires-Dist: pommes
Provides-Extra: dev
Requires-Dist: pytest>=7.0.0; extra == "dev"
Requires-Dist: black>=23.0.0; extra == "dev"
Requires-Dist: isort>=5.10.0; extra == "dev"
Dynamic: license-file
